pygaze/__init__.py
pygaze/gaze_estimator.py
pygaze/pygaze.py
pygaze/transforms.py
pygaze/utils.py
pygaze/common/__init__.py
pygaze/common/camera.py
pygaze/common/eye.py
pygaze/common/face.py
pygaze/common/face_model.py
pygaze/common/face_model_mediapipe.py
pygaze/common/face_parts.py
pygaze/config/__init__.py
pygaze/config/eth-xgaze.yaml
pygaze/data/calib/sample_params.yaml
pygaze/data/normalized_camera_params/eth-xgaze.yaml
pygaze/head_pose_estimation/__init__.py
pygaze/head_pose_estimation/face_landmark_estimator.py
pygaze/head_pose_estimation/head_pose_normalizer.py
pygaze/models/__init__.py
pygaze-1.2.2.dist-info/LICENSE
pygaze-1.2.2.dist-info/METADATA
pygaze-1.2.2.dist-info/WHEEL
pygaze-1.2.2.dist-info/top_level.txt
pygaze-1.2.2.dist-info/RECORD
