Metadata-Version: 2.1
Name: pygaze
Version: 1.2.2
Summary: pygaze is a gaze estimation framework for python based on eth-xgaze.
Home-page: https://github.com/padmalcom/pygaze
Author: Jonas Freiknecht
Author-email: j.freiknecht@googlemail.com
License: MIT
Classifier: Development Status :: 4 - Beta
Classifier: Intended Audience :: Developers
Classifier: License :: OSI Approved :: MIT License
Classifier: Operating System :: OS Independent
Classifier: Programming Language :: Python :: 3.8
Classifier: Programming Language :: Python :: 3.9
Classifier: Programming Language :: Python :: 3.10
Requires-Python: >=3.8
License-File: LICENSE
Requires-Dist: loguru (>=0.6.0)
Requires-Dist: mediapipe (>=0.9.0.1)
Requires-Dist: omegaconf (>=2.3.0)
Requires-Dist: scipy (>=1.9.3)
Requires-Dist: timm (>=0.6.12)
Requires-Dist: torch (>=1.13.0)
